README.md
setup.py
concurrent_helper/__init__.py
concurrent_helper/process_bar.py
concurrent_helper/run_with_concurrent.py
concurrent_helper/run_with_message_queue.py
concurrent_helper.egg-info/PKG-INFO
concurrent_helper.egg-info/SOURCES.txt
concurrent_helper.egg-info/dependency_links.txt
concurrent_helper.egg-info/requires.txt
concurrent_helper.egg-info/top_level.txt