Metadata-Version: 2.1
Name: concurrent-helper
Version: 1.0.2
Summary: The Simplest and Most Powerful Concurrent Helper
Home-page: https://github.com/ChuanqiTan/concurrent_helper
Author: Chuanqi Tan
Author-email: chuanqi.tan@gmail.com
License: MIT
Keywords: concurrent run_with_message_queue run_with_concurrent multithread multiprocess
Platform: UNKNOWN
